LICENSE
README.md
setup.py
SecForm.egg-info/PKG-INFO
SecForm.egg-info/SOURCES.txt
SecForm.egg-info/dependency_links.txt
SecForm.egg-info/top_level.txt
sec_form/SecForm.py
sec_form/__init__.py